hyperonnx/__init__.py
hyperonnx/auto.py
hyperonnx/function_rewriter.py
hyperonnx/hyper_export.py
hyperonnx/patch.py
hyperonnx/torch_export.py
hyperonnx/typing.py
hyperonnx/utils.py
hyperonnx/exporter/__init__.py
hyperonnx/exporter/dynamo.py
hyperonnx/exporter/torchscript.py
hyperonnx/exporter/utils.py
hyperonnx-1.0.0.dist-info/licenses/LICENSE
hyperonnx-1.0.0.dist-info/WHEEL
hyperonnx-1.0.0.dist-info/METADATA
hyperonnx-1.0.0.dist-info/RECORD
