Metadata-Version: 2.4
Name: hyperonnx
Version: 1.0.0
Summary: Copyright (C) 2025 The HYPERONNX Authors.
Author-email: Wenyi Tang <wenyitang@outlook.com>
Requires-Python: >=3.11
Classifier: License :: OSI Approved :: Apache Software License
Classifier: Topic :: Scientific/Engineering :: Artificial Intelligence
Classifier: Topic :: Software Development
License-File: LICENSE
Requires-Dist: onnxifier>=2.0.0
Requires-Dist: onnxscript
Requires-Dist: onnx>=1.18.0
Requires-Dist: torch
Requires-Dist: mypy ; extra == "test"
Requires-Dist: onnxruntime ; extra == "test"
Requires-Dist: pre-commit ; extra == "test"
Requires-Dist: pyright>=1.1.408 ; extra == "test"
Requires-Dist: pytest ; extra == "test"
Requires-Dist: pytest-cov ; extra == "test"
Requires-Dist: torchvision ; extra == "test"
Project-URL: Docs, https://loseall.github.io/hyperonnx
Project-URL: Home, https://github.com/LoSealL/hyperonnx
Provides-Extra: test
